{"coredata": {"prism:url": "https://api.elsevier.com/content/article/pii/S0091674918303178", "dc:identifier": "doi:10.1016/j.jaci.2018.02.025", "eid": "1-s2.0-S0091674918303178", "prism:doi": "10.1016/j.jaci.2018.02.025", "pii": "S0091-6749(18)30317-8", "dc:title": "Machine learning, natural language programming, and electronic health records: The next step in the artificial intelligence journey? ", "prism:publicationName": "Journal of Allergy and Clinical Immunology", "prism:aggregationType": "Journal", "pubType": "\n               Beyond the frontiers\n            ", "prism:issn": "00916749", "prism:volume": "141", "prism:issueIdentifier": "6", "prism:startingPage": "2019", "prism:endingPage": "2021.e1", "prism:pageRange": "2019-2021.e1", "prism:number": "6", "dc:format": "application/json", "prism:coverDate": "2018-06-30", "prism:coverDisplayDate": "June 2018", "prism:copyright": "\u00a9 2018 American Academy of Allergy, Asthma & Immunology", "prism:publisher": "American Academy of Allergy, Asthma & Immunology", "dc:creator": [{"@_fa": "true", "$": "Mehta, Neil"}, {"@_fa": "true", "$": "Devarakonda, Murthy V."}], "dc:description": null, "openaccess": "0", "openaccessArticle": false, "openaccessType": null, "openArchiveArticle": false, "openaccessSponsorName": null, "openaccessSponsorType": null, "openaccessUserLicense": null, "dcterms:subject": [{"@_fa": "true", "$": "Machine learning"}, {"@_fa": "true", "$": "artificial intelligence"}, {"@_fa": "true", "$": "electronic health records"}, {"@_fa": "true", "$": "natural language processing"}, {"@_fa": "true", "$": "medical computer science"}], "link": [{"@href": "https://api.elsevier.com/content/article/pii/S0091674918303178", "@rel": "self", "@_fa": "true"}, {"@href": "https://www.sciencedirect.com/science/article/pii/S0091674918303178", "@rel": "scidir", "@_fa": "true"}]}, "scopus-id": "85044734548", "scopus-eid": "2-s2.0-85044734548", "pubmed-id": "29518424", "link": {"@href": "https://api.elsevier.com/content/abstract/scopus_id/85044734548", "@rel": "abstract"}, "originalText": {"xocs:doc": {"xocs:meta": {"xocs:open-access": {"xocs:oa-article-status": {"@is-open-access": "0", "@is-open-archive": "0"}}, "xocs:available-online-date": {"@yyyymmdd": "20180305", "$": "2018-03-05"}}}}}