{"coredata": {"prism:url": "https://api.elsevier.com/content/article/pii/S0165027010002803", "dc:identifier": "doi:10.1016/j.jneumeth.2010.05.020", "eid": "1-s2.0-S0165027010002803", "prism:doi": "10.1016/j.jneumeth.2010.05.020", "pii": "S0165-0270(10)00280-3", "dc:title": "Automatic epileptic seizure detection in EEGs based on line length feature and artificial neural networks ", "prism:publicationName": "Journal of Neuroscience Methods", "prism:aggregationType": "Journal", "prism:issn": "01650270", "prism:volume": "191", "prism:issueIdentifier": "1", "prism:startingPage": "101", "prism:endingPage": "109", "prism:pageRange": "101-109", "prism:number": "1", "dc:format": "application/json", "prism:coverDate": "2010-08-15", "prism:coverDisplayDate": "15 August 2010", "prism:copyright": "Copyright \u00a9 2010 Elsevier B.V. All rights reserved.", "prism:publisher": "Elsevier B.V.", "dc:creator": [{"@_fa": "true", "$": "Guo, Ling"}, {"@_fa": "true", "$": "Rivero, Daniel"}, {"@_fa": "true", "$": "Dorado, Juli\u00e1n"}, {"@_fa": "true", "$": "Rabu\u00f1al, Juan R."}, {"@_fa": "true", "$": "Pazos, Alejandro"}], "dc:description": "\n               Abstract\n               \n                  About 1% of the people in the world suffer from epilepsy. The main characteristic of epilepsy is the recurrent seizures. Careful analysis of the electroencephalogram (EEG) recordings can provide valuable information for understanding the mechanisms behind epileptic disorders. Since epileptic seizures occur irregularly and unpredictably, automatic seizure detection in EEG recordings is highly required. Wavelet transform (WT) is an effective analysis tool for non-stationary signals, such as EEGs. The line length feature reflects the waveform dimensionality changes and is a measure sensitive to variation of the signal amplitude and frequency. This paper presents a novel method for automatic epileptic seizure detection, which uses line length features based on wavelet transform multiresolution decomposition and combines with an artificial neural network (ANN) to classify the EEG signals regarding the existence of seizure or not. To the knowledge of the authors, there exists no similar work in the literature. A famous public dataset was used to evaluate the proposed method. The high accuracy obtained for three different classification problems testified the great success of the method.\n               \n            ", "openaccess": "0", "openaccessArticle": false, "openaccessType": null, "openArchiveArticle": false, "openaccessSponsorName": null, "openaccessSponsorType": null, "openaccessUserLicense": null, "dcterms:subject": [{"@_fa": "true", "$": "Electroencephalogram (EEG)"}, {"@_fa": "true", "$": "Epileptic seizure detection"}, {"@_fa": "true", "$": "Discrete wavelet transform (DWT)"}, {"@_fa": "true", "$": "Line length feature"}, {"@_fa": "true", "$": "Artificial neural network (ANN)"}], "link": [{"@href": "https://api.elsevier.com/content/article/pii/S0165027010002803", "@rel": "self", "@_fa": "true"}, {"@href": "https://www.sciencedirect.com/science/article/pii/S0165027010002803", "@rel": "scidir", "@_fa": "true"}]}, "scopus-id": "77955054723", "scopus-eid": "2-s2.0-77955054723", "pubmed-id": "20595035", "link": {"@href": "https://api.elsevier.com/content/abstract/scopus_id/77955054723", "@rel": "abstract"}, "originalText": {"xocs:doc": {"xocs:meta": {"xocs:open-access": {"xocs:oa-article-status": {"@is-open-access": "0", "@is-open-archive": "0"}}, "xocs:available-online-date": {"@yyyymmdd": "20100602", "$": "2010-06-02"}}}}}