{"coredata": {"prism:url": "https://api.elsevier.com/content/article/pii/S0003267009000191", "dc:identifier": "doi:10.1016/j.aca.2009.01.009", "eid": "1-s2.0-S0003267009000191", "prism:doi": "10.1016/j.aca.2009.01.009", "pii": "S0003-2670(09)00019-1", "dc:title": "Artificial neural networks in foodstuff analyses: Trends and perspectives A review ", "prism:publicationName": "Analytica Chimica Acta", "prism:aggregationType": "Journal", "pubType": "\n               Review\n            ", "prism:issn": "00032670", "prism:volume": "635", "prism:issueIdentifier": "2", "prism:startingPage": "121", "prism:endingPage": "131", "prism:pageRange": "121-131", "prism:number": "2", "dc:format": "application/json", "prism:coverDate": "2009-03-09", "prism:coverDisplayDate": "9 March 2009", "prism:copyright": "Copyright \u00a9 2009 Elsevier B.V. All rights reserved.", "prism:publisher": "Elsevier B.V.", "dc:creator": [{"@_fa": "true", "$": "Marini, Federico"}], "dc:description": "\n               Abstract\n               \n                  Artificial neural networks are a family of non-linear computational methods, loosely inspired by the human brain, that have found application in an increasing number of fields of analytical chemistry and specifically of food control. In this review, the main neural network architectures are described and examples of their application to solve food analytical problems are presented, together with some considerations about their uses and misuses.\n               \n            ", "openaccess": "0", "openaccessArticle": false, "openaccessType": null, "openArchiveArticle": false, "openaccessSponsorName": null, "openaccessSponsorType": null, "openaccessUserLicense": null, "dcterms:subject": [{"@_fa": "true", "$": "Food analysis"}, {"@_fa": "true", "$": "Chemometrics"}, {"@_fa": "true", "$": "Artificial neural networks"}, {"@_fa": "true", "$": "Food science"}], "link": [{"@href": "https://api.elsevier.com/content/article/pii/S0003267009000191", "@rel": "self", "@_fa": "true"}, {"@href": "https://www.sciencedirect.com/science/article/pii/S0003267009000191", "@rel": "scidir", "@_fa": "true"}]}, "scopus-id": "59649087410", "scopus-eid": "2-s2.0-59649087410", "pubmed-id": "19216869", "link": {"@href": "https://api.elsevier.com/content/abstract/scopus_id/59649087410", "@rel": "abstract"}, "originalText": {"xocs:doc": {"xocs:meta": {"xocs:open-access": {"xocs:oa-article-status": {"@is-open-access": "0", "@is-open-archive": "0"}}, "xocs:available-online-date": {"@yyyymmdd": "20090110", "$": "2009-01-10"}}}}}