{"coredata": {"prism:url": "https://api.elsevier.com/content/article/pii/S1364661314000862", "dc:identifier": "doi:10.1016/j.tics.2014.04.004", "eid": "1-s2.0-S1364661314000862", "prism:doi": "10.1016/j.tics.2014.04.004", "pii": "S1364-6613(14)00086-2", "dc:title": "Cognition from the bottom up: on biological inspiration, body morphology, and soft materials ", "prism:publicationName": "Trends in Cognitive Sciences", "prism:aggregationType": "Journal", "pubType": "\n               Opinion\n            ", "prism:issn": "13646613", "prism:volume": "18", "prism:issueIdentifier": "8", "prism:startingPage": "404", "prism:endingPage": "413", "prism:pageRange": "404-413", "prism:number": "8", "dc:format": "application/json", "prism:coverDate": "2014-08-31", "prism:coverDisplayDate": "August 2014", "prism:copyright": "Copyright \u00a9 2014 Elsevier Ltd. All rights reserved.", "prism:publisher": "Elsevier Ltd.", "dc:creator": [{"@_fa": "true", "$": "Pfeifer, Rolf"}, {"@_fa": "true", "$": "Iida, Fumiya"}, {"@_fa": "true", "$": "Lungarella, Max"}], "dc:description": "\n               \n                  Traditionally, in cognitive science the emphasis is on studying cognition from a computational point of view. Studies in biologically inspired robotics and embodied intelligence, however, provide strong evidence that cognition cannot be analyzed and understood by looking at computational processes alone, but that physical system\u2013environment interaction needs to be taken into account. In this opinion article, we review recent progress in cognitive developmental science and robotics, and expand the notion of embodiment to include soft materials and body morphology in the big picture. We argue that we need to build our understanding of cognition from the bottom up; that is, all the way from how our body is physically constructed.\n               \n            ", "openaccess": "0", "openaccessArticle": false, "openaccessType": null, "openArchiveArticle": false, "openaccessSponsorName": null, "openaccessSponsorType": null, "openaccessUserLicense": null, "dcterms:subject": [{"@_fa": "true", "$": "embodied intelligence"}, {"@_fa": "true", "$": "morphological computation"}, {"@_fa": "true", "$": "bio-inspired soft robotics"}, {"@_fa": "true", "$": "developmental sciences and robotics"}], "link": [{"@href": "https://api.elsevier.com/content/article/pii/S1364661314000862", "@rel": "self", "@_fa": "true"}, {"@href": "https://www.sciencedirect.com/science/article/pii/S1364661314000862", "@rel": "scidir", "@_fa": "true"}]}, "scopus-id": "84904751819", "scopus-eid": "2-s2.0-84904751819", "pubmed-id": "24839893", "link": {"@href": "https://api.elsevier.com/content/abstract/scopus_id/84904751819", "@rel": "abstract"}, "originalText": {"xocs:doc": {"xocs:meta": {"xocs:open-access": {"xocs:oa-article-status": {"@is-open-access": "0", "@is-open-archive": "0"}}, "xocs:available-online-date": {"@yyyymmdd": "20140516", "$": "2014-05-16"}}}}}